{"2024-10-09":{"小麦":{"全国":2424},"早籼稻":{"全国":2735},"中晚籼稻":{"全国":2654,"江苏":2698,"浙江":2660,"安徽":2617,"福建":2791,"江西":2681,"河南":2456,"湖北":2589,"湖南":2738,"广东":3268,"广西":3184,"重庆":2643,"四川":2666,"贵州":2997,"云南":2981},"粳稻":{"全国":2705},"玉米":{"全国":2093},"大豆":{"全国":4004},"油菜籽":{"全国":5964}},"2024-09-25":{"小麦":{"全国":2434,"河北":2408,"山西":2352,"江苏":2437,"安徽":2422,"山东":2424,"河南":2432,"湖北":2449,"四川":2523,"陕西":2430,"甘肃":2490,"新疆":2429},"早籼稻":{"全国":2798,"浙江":2613,"安徽":2698,"福建":2643,"江西":2678,"湖北":2660,"湖南":2729,"广东":3100,"广西":2840},"中晚籼稻":{"全国":2754,"江苏":2778,"浙江":2660,"安徽":2652,"福建":2795,"江西":2721,"河南":2471,"湖北":2595,"湖南":2755,"广东":3268,"广西":3187,"重庆":2660,"四川":2676,"贵州":2965,"云南":3033},"粳稻":{"全国":2785},"玉米":{"全国":2186},"大豆":{"全国":4507},"油菜籽":{"全国":5951}},"2024-09-18":{"小麦":{"全国":2447,"河北":2430,"山西":2368,"江苏":2443,"安徽":2430,"山东":2443,"河南":2446,"湖北":2457,"四川":2536,"陕西":2447,"甘肃":2510,"新疆":2433},"早籼稻":{"全国":2803,"浙江":2613,"安徽":2711,"福建":2643,"江西":2680,"湖北":2664,"湖南":2742,"广东":3100,"广西":2845},"中晚籼稻":{"全国":2767},"粳稻":{"全国":2790},"玉米":{"全国":2247},"大豆":{"全国":4613},"油菜籽":{"全国":5956}},"2024-09-11":{"小麦":{"全国":2452,"河北":2435,"山西":2380,"江苏":2446,"安徽":2437,"山东":2447,"河南":2450,"湖北":2458,"四川":2535,"陕西":2451,"甘肃":2517,"新疆":2441},"早籼稻":{"全国":2809,"浙江":2613,"安徽":2719,"福建":2643,"江西":2685,"湖北":2684,"湖南":2757,"广东":3105,"广西":2836},"中晚籼稻":{"全国":2777},"粳稻":{"全国":2794},"玉米":{"全国":2276},"大豆":{"全国":4613},"油菜籽":{"全国":5968}},"2024-09-04":{"小麦":{"全国":2456,"河北":2437,"山西":2392,"江苏":2453,"安徽":2440,"山东":2450,"河南":2453,"湖北":2457,"四川":2544,"陕西":2464,"甘肃":2512,"新疆":2447},"早籼稻":{"全国":2815,"浙江":2615,"安徽":2723,"福建":2643,"江西":2690,"湖北":2721,"湖南":2772,"广东":3105,"广西":2836},"中晚籼稻":{"全国":2792},"粳稻":{"全国":2796},"玉米":{"全国":2292},"大豆":{"全国":4617},"油菜籽":{"全国":5968}},"2024-08-28":{"小麦":{"全国":2460,"河北":2441,"山西":2395,"江苏":2457,"安徽":2444,"山东":2451,"河南":2454,"湖北":2458,"四川":2557,"陕西":2467,"甘肃":2526,"新疆":2448},"早籼稻":{"全国":2819,"浙江":2635,"安徽":2724,"福建":2643,"江西":2698,"湖北":2719,"湖南":2781,"广东":3106,"广西":2838},"中晚籼稻":{"全国":2806},"粳稻":{"全国":2797},"玉米":{"全国":2301},"大豆":{"全国":4634},"油菜籽":{"全国":5968}},"2024-08-21":{"小麦":{"全国":2463,"河北":2442,"山西":2402,"江苏":2463,"山东":2450,"河南":2453,"湖北":2459,"四川":2565,"陕西":2477,"甘肃":2527,"新疆":2453},"早籼稻":{"全国":2823,"浙江":2633,"安徽":2725,"福建":2628,"江西":2707,"湖北":2744,"湖南":2790,"广东":3106,"广西":2832},"中晚籼稻":{"全国":2817},"粳稻":{"全国":2799},"玉米":{"全国":2306},"大豆":{"全国":4649},"油菜籽":{"全国":5960}},"2024-08-14":{"小麦":{"全国":2465,"河北":2438,"山西":2414,"江苏":2466,"安徽":2452,"山东":2448,"河南":2459,"湖北":2466,"四川":2573,"陕西":2490,"甘肃":2527,"新疆":2442},"早籼稻":{"全国":2824,"浙江":2628,"安徽":2727,"福建":2628,"江西":2711,"湖北":2775,"湖南":2787,"广东":3105,"广西":2835},"中晚籼稻":{"全国":2831},"粳稻":{"全国":2802},"玉米":{"全国":2324},"大豆":{"全国":4665},"油菜籽":{"全国":5954}},"2024-08-07":{"小麦":{"全国":2474,"河北":2451,"山西":2430,"江苏":2467,"安徽":2458,"山东":2466,"河南":2466,"湖北":2473,"四川":2572,"陕西":2502,"甘肃":2551,"新疆":2445},"早籼稻":{"全国":2824,"浙江":2627,"安徽":2729,"福建":2628,"江西":2714,"湖北":2766,"湖南":2780,"广东":3104,"广西":2840},"中晚籼稻":{"全国":2840},"粳稻":{"全国":2808},"玉米":{"全国":2343},"大豆":{"全国":4676},"油菜籽":{"全国":5970}},"2024-07-31":{"小麦":{"全国":2479,"河北":2458,"山西":2440,"江苏":2467,"安徽":2461,"山东":2472,"河南":2467,"湖北":2469,"四川":2579,"陕西":2508,"甘肃":2570,"新疆":2452},"早籼稻":{"全国":2817,"浙江":2631,"安徽":2728,"福建":2608,"江西":2706,"湖北":2789,"湖南":2781,"广东":3104,"广西":2811},"中晚籼稻":{"全国":2843},"粳稻":{"全国":2809},"玉米":{"全国":2362},"大豆":{"全国":4671},"油菜籽":{"全国":5974}},"2024-07-24":{"小麦":{"全国":2483,"河北":2456,"山西":2452,"江苏":2468,"安徽":2461,"山东":2475,"河南":2469,"湖北":2474,"四川":2586,"陕西":2522,"甘肃":2590,"新疆":2463},"早籼稻":{"全国":2816,"浙江":2630,"安徽":2728,"福建":2608,"江西":2699,"湖北":2763,"湖南":2778,"广东":3116,"广西":2807},"中晚籼稻":{"全国":2848},"粳稻":{"全国":2809},"玉米":{"全国":2362},"大豆":{"全国":4671},"油菜籽":{"全国":5975}},"2024-07-17":{"小麦":{"全国":2485,"河北":2456,"山西":2444,"江苏":2472,"安徽":2462,"山东":2473,"河南":2471,"湖北":2482,"四川":2581,"陕西":2527,"甘肃":2612,"新疆":2467},"早籼稻":{"全国":2810},"中晚籼稻":{"全国":2848},"粳稻":{"全国":2809},"玉米":{"全国":2362},"大豆":{"全国":4671},"油菜籽":{"全国":5967}},"2024-07-10":{"小麦":{"全国":2491,"河北":2456,"山西":2446,"江苏":2472,"安徽":2465,"山东":2485,"河南":2472,"湖北":2482,"四川":2586,"陕西":2534,"甘肃":2622,"新疆":2517},"早籼稻":{"全国":2806},"中晚籼稻":{"全国":2850},"粳稻":{"全国":2809},"玉米":{"全国":2389},"大豆":{"全国":4671},"油菜籽":{"全国":5979}},"2024-07-03":{"小麦":{"全国":2487,"河北":2459,"山西":2448,"江苏":2468,"安徽":2465,"山东":2473,"河南":2467,"湖北":2478,"四川":2593,"陕西":2540,"甘肃":2647,"新疆":2510},"早籼稻":{"全国":2808},"中晚籼稻":{"全国":2850},"粳稻":{"全国":2809},"玉米":{"全国":2386},"大豆":{"全国":4676},"油菜籽":{"全国":5878}}}